setup.cfg
setup.py
emailcontent/__init__.py
emailcontent/metadata.py
emailcontent.egg-info/PKG-INFO
emailcontent.egg-info/SOURCES.txt
emailcontent.egg-info/dependency_links.txt
emailcontent.egg-info/entry_points.txt
emailcontent.egg-info/top_level.txt
emailcontent.egg-info/zip-safe