Metadata-Version: 1.0
Name: emailcontent
Version: 0.1dev
Summary: Functionality for extracting content from email messages.
Home-page: UNKNOWN
Author: Karel Antonio Verdecia Ortiz
Author-email: kverdecia@uci.cu
License: LGPL3
Keywords: email rfc822
Platform: UNKNOWN
